bigml_tf_tree.cpython-311-darwin.so
tests/test_construct.py
tests/test_tree.py
tests/__init__.py
tests/utils.py
tests/test_pretrained.py
tests/test_wrappers.py
tests/test_export.py
tests/test_regression.py
sensenet/sensenet_metadata.json.gz
sensenet/pretrained.py
sensenet/accessors.py
sensenet/constants.py
sensenet/__init__.py
sensenet/importers.py
sensenet/load.py
sensenet/layers/tree.py
sensenet/layers/dropblock.py
sensenet/layers/convolutional.py
sensenet/layers/legacy.py
sensenet/layers/__init__.py
sensenet/layers/core.py
sensenet/layers/utils.py
sensenet/layers/yolo.py
sensenet/layers/construct.py
sensenet/layers/block.py
sensenet/layers/extract.py
sensenet/preprocess/categorical.py
sensenet/preprocess/__init__.py
sensenet/preprocess/preprocessor.py
sensenet/preprocess/numeric.py
sensenet/preprocess/image.py
sensenet/models/bundle.py
sensenet/models/__init__.py
sensenet/models/bounding_box.py
sensenet/models/wrappers.py
sensenet/models/settings.py
sensenet/models/image.py
sensenet/models/deepnet.py
bigml_sensenet-0.7.5.dist-info/RECORD
bigml_sensenet-0.7.5.dist-info/WHEEL
bigml_sensenet-0.7.5.dist-info/top_level.txt
bigml_sensenet-0.7.5.dist-info/METADATA
