Metadata-Version: 2.1
Name: bigml-sensenet
Version: 0.7.5
Summary: Network builder for bigml deepnet topologies
Home-page: http://bigml.com/
Author: BigML Team
Author-email: team@bigml.com
Requires-Python: >=3.9
Requires-Dist: tf-keras~=2.16
Requires-Dist: pillow<10.2.1,>=10.2.0
Requires-Dist: scikit-learn<1.4.1,>=1.4
Requires-Dist: pytest<7.5,>=7.4.2
Requires-Dist: tensorflow<2.17,>=2.16
